{
  "dayTours": [
      {
        "id": 2,
        "title": "Ella Day Tour - Departing from Any Location in Sri Lanka",
        "days": "1 days",
        "persons": "20 Person",
        "rating": 5,
        "filecode": "daytour-ella",
        "image": "assets/img/onedayTour/ella/5.jpg",
        "routerLink": "/Elladaystours"
      },
      {
        "id": 6,
        "title": "Galle Day Tour - Departing from Any Location in Sri Lanka",
        "days": "1 days",
        "persons": "20 Person",
        "rating": 5,
        "filecode": "daytour-galle",
        "image": "assets/img/onedayTour/Galle/7.jpg",
        "routerLink": "/Galledaystours"
      },
      {
        "id": 7,
        "title": "Kandy Day Tour - Departing from Any Location in Sri Lanka",
        "days": "1 days",
        "persons": "20 Person",
        "rating": 5,
        "filecode": "daytour-kandy",
        "image": "assets/img/onedayTour/kandy/3.jpg",
        "routerLink": "/Kandydaystours"
      },
      {
        "id": 8,
        "title": "Sigiriya Day Tour - Departing from Any Location in Sri Lanka",
        "days": "1 days",
        "persons": "20 Person",
        "rating": 5,
        "filecode": "daytour-sigiriya",
        "image": "assets/img/onedayTour/Sigiriya/3.jpg",
        "routerLink": "/Sirgiriyadaystours"
      }
],
"multiDayTours": [
    {
      "id": 1,
      "title": "Sigiriya and Kandy 2 Days Private Tour with HB Deluxe Accommodation",
      "days": "2 days",
      "persons": "20 Person",
      "rating": 4.5,
      "filecode": "twodaystours",
      "image": "assets/img/package-3.jpg",
      "routerLink": "/twodaystours"
    },
    {
      "id": 3,
      "title": "Sri Lanka 5 Days Tour with 4 Star Hotels and Private Transportation",
      "days": "5 days",
      "persons": "20 Person",
      "rating": 5,
      "filecode": "fivedaystours",
      "image": "assets/img/package-4.jpg",
      "routerLink": "/fivedaystours"
    },
    {
      "id": 4,
      "title": "Sri Lanka 7 Days Tour with 4 Star Hotels and Private Transportation",
      "days": "7 days",
      "persons": "20 Person",
      "rating": 5,
      "filecode": "sevendaystours",
      "image": "assets/img/package-1.jpg",
      "routerLink": "/sevendaystours"
    },
    {
      "id": 5,
      "title": "Sri Lanka 10 Days Tour with 4 Star Hotels and Private Transportation",
      "days": "10 days",
      "persons": "20 Person",
      "rating": 5,
      "filecode": "tendaystours",
      "image": "assets/img/package-2.jpg",
      "routerLink": "/tendaystours"
    }
  ]
}
